Workbook

Sheet Resumo
A1: GMAT3 | Valuation por Multiplos
A3: Tese: GMAT3 parece moderadamente descontada frente a peers LatAm saudáveis, mas o 1T26 reduz a convicção por SSS negativo, deflação alimentar e trade-off entre margem e volume. O valuation sugere upside, não uma recomendação agressiva.
A6: Métrica | B6: Valor | C6: Leitura | E6: Bloco | F6: Mensagem para slide | G6: Como defender
A7: Preço atual | B7: ='Valuation'!I7 | C7: Preço de tela usado no modelo | E7: Os Números | F7: Preço justo de R$ 4,83 vs. R$ 4,26; upside de 13,3%. | G7: Não vender como compra forte; é upside moderado.
A8: Preço justo base | B8: ='Valuation'!H7 | C8: LatAm ex-distressed | E8: O Spread | F8: GMAT3 negocia abaixo da mediana LatAm ex-distressed. | G8: Desconto é parcialmente justificado pelo 1T26 fraco.
A9: Upside / Downside | B9: ='Valuation'!J7 | C9: Moderado, com cautela operacional | E9: A Tese | F9: Qualidade regional e maturação sustentam upside, mas SSS negativo reduz convicção. | G9: Tese construtiva com cautela operacional.
A10: EV/EBITDA aplicado | B10: ='Valuation'!B7 | C10: Mediana LatAm ex-distressed
A11: GMAT3 EV/EBITDA atual | B11: ='Multiplos'!E6 | C11: Abaixo da mediana base
A12: GMAT3 P/L | B12: ='Multiplos'!F6 | C12: P/L complementar

Sheet Base Normalizada
A1: Checkpoint 2 | Base Normalizada
A3: Esta aba documenta a base usada no valuation. Brasil usa dados 1T26 anualizados; LatAm usa métricas trailing via yfinance. O objetivo é deixar claro o basis de cada número, evitando misturar dados sem explicar a data-base.
A6: Ticker | B6: Empresa | C6: País | D6: Papel | E6: Qualidade | F6: Incluído? | G6: Moeda | H6: Base EBITDA | I6: Base Lucro Líquido | J6: EV/EBITDA | K6: P/L | L6: Status P/L | M6: Fonte
A7: GMAT3.SA | B7: Grupo Mateus | C7: Brazil | D7: Target | E7: Target | F7: FALSE | G7: BRL | H7: 1Q26 annualized | I7: 1Q26 annualized | J7: 6.5838771 | K7: 11.500239 | L7: Calculated | M7: notebook_01_annualized_1q26
A8: ASAI3.SA | B8: Assai | C8: Brazil | D8: Domestic Core Peer | E8: Core Peer | F8: TRUE | G8: BRL | H8: 1Q26 annualized | I8: 1Q26 annualized | J8: 6.1047965 | K8: 17.832164 | L8: Calculated | M8: notebook_01_annualized_1q26
A9: PCAR3.SA | B9: GPA | C9: Brazil | D9: Domestic Distressed Peer | E9: Distressed / Turnaround Peer | F9: TRUE | G9: BRL | H9: 1Q26 annualized | I9: 1Q26 annualized | J9: 2.2974641 | L9: N.M. - negative earnings | M9: notebook_01_annualized_1q26
A10: WALMEX.MX | B10: Walmart de Mexico | C10: Mexico | D10: LatAm Peer | E10: High Quality LatAm Peer | F10: TRUE | G10: MXN | H10: yfinance trailing EBITDA | I10: yfinance trailing net income | J10: 9.841 | K10: 18.222221 | L10: Calculated | M10: yfinance
A11: CHDRAUIB.MX | B11: Grupo Comercial Chedraui | C11: Mexico | D11: LatAm Peer | E11: LatAm Food Retail Peer | F11: TRUE | G11: MXN | H11: yfinance trailing EBITDA | I11: yfinance trailing net income | J11: 7.217 | K11: 14.390602 | L11: Calculated | M11: yfinance
A12: SORIANAB.MX | B12: Organizacion Soriana | C12: Mexico | D12: LatAm Peer | E12: LatAm Food Retail Peer | F12: TRUE | G12: MXN | H12: yfinance trailing EBITDA | I12: yfinance trailing net income | J12: 7.398 | K12: 12.700729 | L12: Calculated | M12: yfinance
A13: CENCOSUD.SN | B13: Cencosud | C13: Chile | D13: LatAm Peer | E13: LatAm Multi-format Retail Peer | F13: TRUE | G13: CLP | H13: yfinance trailing EBITDA | I13: yfinance trailing net income | J13: 10.864 | K13: 20.70428 | L13: Calculated | M13: yfinance

Sheet Ajuste Multiplo
A1: Racional do Multiplo Aplicado
A3: O múltiplo aplicado não é uma mediana mecânica. A mediana LatAm ex-distressed é o ponto de partida; avaliamos prêmio por qualidade operacional, mas neutralizamos esse prêmio por causa dos sinais fracos do 1T26.
A6: Etapa | B6: Efeito no múltiplo | C6: Múltiplo após etapa | D6: Racional
A7: Starting point: LatAm ex-distressed median | B7: 7.398 | C7: 7.398 | D7: Cleanest peer set: excludes GPA stress and expands beyond one domestic peer.
A8: Operational quality premium considered | B8: 0.2 | C8: 7.598 | D8: Regional strength, store maturation potential and logistics/distribution relevance support a possible premium.
A9: 1T26 operating caution discount | B9: -0.2 | C9: 7.398 | D9: SSS -7.3%, food deflation, weaker demand and margin-over-volume trade-off reduce conviction.
A10: Final applied base multiple | B10: 0 | C10: 7.398 | D10: Keep 7.4x base multiple: moderate upside, but no aggressive premium until SSS and operating leverage improve.
A13: Conclusão: mantemos 7,4x EV/EBITDA no caso base. GMAT3 tem atributos para negociar melhor que uma mediana contaminada por GPA, mas o 1T26 não justifica aplicar prêmio agressivo até SSS, volume e alavancagem operacional melhorarem.

Sheet Peer Group
A1: Peer Group e Tratamento Analitico
A3: Ticker | B3: Empresa | C3: Pais | D3: Bolsa | E3: Moeda | F3: Segmento | G3: Papel | H3: Qualidade | I3: Entra no calculo? | J3: Justificativa
A4: GMAT3.SA | B4: Grupo Mateus | C4: Brazil | D4: B3 | E4: BRL | F4: Food Retail and Cash & Carry | G4: Target | H4: Target | I4: FALSE | J4: Target company to be valued
A5: ASAI3.SA | B5: Assai | C5: Brazil | D5: B3 | E5: BRL | F5: Cash & Carry | G5: Domestic Core Peer | H5: Core Peer | I5: TRUE | J5: Closest listed Brazilian cash and carry comparable
A6: PCAR3.SA | B6: GPA | C6: Brazil | D6: B3 | E6: BRL | F6: Food Retail | G6: Domestic Distressed Peer | H6: Distressed / Turnaround Peer | I6: TRUE | J6: Listed Brazilian food retail peer but distressed and should be scenario-tested
A7: CRFB3.SA | B7: Carrefour Brasil / Atacadao | C7: Brazil | D7: B3 delisted | E7: BRL | F7: Food Retail and Cash & Carry | G7: Domestic Operational Peer | H7: Delisted / Operational Reference | I7: FALSE | J7: Operationally relevant but not a current trading comparable after delisting
A8: WALMEX.MX | B8: Walmart de Mexico | C8: Mexico | D8: BMV | E8: MXN | F8: Food Retail and Clubs | G8: LatAm Peer | H8: High Quality LatAm Peer | I8: TRUE | J8: Large LatAm food retail and club-store operator
A9: CHDRAUIB.MX | B9: Grupo Comercial Chedraui | C9: Mexico | D9: BMV | E9: MXN | F9: Food Retail | G9: LatAm Peer | H9: LatAm Food Retail Peer | I9: TRUE | J9: Mexican food retail operator with Mexico and US exposure
A10: SORIANAB.MX | B10: Organizacion Soriana | C10: Mexico | D10: BMV | E10: MXN | F10: Food Retail | G10: LatAm Peer | H10: LatAm Food Retail Peer | I10: TRUE | J10: Mexican supermarket and food retail operator
A11: CENCOSUD.SN | B11: Cencosud | C11: Chile | D11: Santiago | E11: CLP | F11: Food Retail and Multi-format Retail | G11: LatAm Peer | H11: LatAm Multi-format Retail Peer | I11: TRUE | J11: Large Chilean and regional retail operator with food retail exposure

Sheet Peer Selection
A1: Peer Selection | Inclusões e Exclusões
A3: O peer group parte de um universo amplo de varejo alimentar, atacarejo e warehouse clubs. A mediana principal prioriza empresas listadas com maior comparabilidade regional e operacional. Nomes globais ou com modelo muito diferente ficam fora da mediana, mas podem ser usados como contexto qualitativo.
A6: Empresa | B6: Ticker | C6: País | D6: Segmento | E6: Decisão | F6: Racional
A7: Walmart Inc. | B7: WMT | C7: United States | D7: Global food retail and mass retail | E7: Excluded from main median | F7: Very large developed-market global retailer; scale, country risk, format mix and valuation profile are not directly comparable to GMAT3.
A8: Costco Wholesale | B8: COST | C8: United States | D8: Warehouse club / membership retail | E8: Excluded from main median | F8: High-quality global warehouse club with membership model and structurally premium multiple; useful as context but not appropriate for the main LatAm food retail median.
A9: Kroger | B9: KR | C9: United States | D9: Supermarket / grocery retail | E9: Excluded from main median | F9: US grocery operator in a mature developed market; operating model and market structure differ from Brazilian cash-and-carry and regional food retail.
A10: BJ's Wholesale Club | B10: BJ | C10: United States | D10: Warehouse club / membership retail | E10: Excluded from main median | F10: Closer to cash-and-carry in format but US membership-club economics and developed-market risk profile reduce comparability.
A11: Carrefour SA | B11: CA.PA | C11: France | D11: Global food retail | E11: Excluded from main median | F11: Global multi-country retailer; consolidated multiple reflects Europe and global portfolio, not specifically Brazilian Atacadao economics.
A12: Carrefour Brasil / Atacadao | B12: CRFB3.SA | C12: Brazil | D12: Food retail and cash-and-carry | E12: Operational reference only | F12: Highly relevant operationally, but CRFB3 was delisted and no longer provides a current listed trading multiple.
A13: Casino Guichard-Perrachon | B13: CO.PA | C13: France | D13: Food retail / distressed retail | E13: Excluded from main median | F13: Financial distress, restructuring and European exposure make the multiple unsuitable as a normalized food retail benchmark.
A14: Sendas / Assai | B14: ASAI3.SA | C14: Brazil | D14: Cash-and-carry | E14: Included | F14: Closest listed Brazilian cash-and-carry peer and the cleanest domestic benchmark for GMAT3.
A15: GPA | B15: PCAR3.SA | C15: Brazil | D15: Food retail | E15: Included as stress case | F15: Listed Brazilian food retail peer, but negative earnings and turnaround profile mean it should be used as stress/downside reference, not central fair-value benchmark.
A16: Walmart de Mexico | B16: WALMEX.MX | C16: Mexico | D16: Food retail and clubs | E16: Included | F16: High-quality LatAm food retail and club-store operator; useful for expanded regional peer set.
A17: Grupo Comercial Chedraui | B17: CHDRAUIB.MX | C17: Mexico | D17: Food retail | E17: Included | F17: Listed LatAm food retailer with grocery exposure and available market multiples.
... A19: Cencosud | B19: CENCOSUD.SN | C19: Chile | D19: Food retail and multi-format retail | E19: Included | F19: Large listed LatAm retailer with food retail exposure, though multi-format nature requires comparability caution.

Sheet Multiplos
A1: Multiplos de Mercado
A3: Ticker | B3: Empresa | C3: Pais | D3: Tipo | E3: EV/EBITDA | F3: P/L | G3: Status P/L | H3: Incluido? | I3: Fonte
A4: PCAR3.SA | B4: GPA | C4: Brazil | D4: Distressed / Turnaround Peer | E4: 2.2974641 | F4: N.M. | G4: N.M. - negative earnings | H4: TRUE | I4: notebook_01_annualized_1q26
A5: ASAI3.SA | B5: Assai | C5: Brazil | D5: Core Peer | E5: 6.1047965 | F5: 17.832164 | G5: Calculated | H5: TRUE | I5: notebook_01_annualized_1q26
A6: GMAT3.SA | B6: Grupo Mateus | C6: Brazil | D6: Target | E6: 6.5838771 | F6: 11.500239 | G6: Calculated | H6: FALSE | I6: notebook_01_annualized_1q26
A7: CHDRAUIB.MX | B7: Grupo Comercial Chedraui | C7: Mexico | D7: LatAm Food Retail Peer | E7: 7.217 | F7: 14.390602 | G7: Calculated | H7: TRUE | I7: yfinance
A8: SORIANAB.MX | B8: Organizacion Soriana | C8: Mexico | D8: LatAm Food Retail Peer | E8: 7.398 | F8: 12.700729 | G8: Calculated | H8: TRUE | I8: yfinance
A9: WALMEX.MX | B9: Walmart de Mexico | C9: Mexico | D9: High Quality LatAm Peer | E9: 9.841 | F9: 18.222221 | G9: Calculated | H9: TRUE | I9: yfinance
A10: CENCOSUD.SN | B10: Cencosud | C10: Chile | D10: LatAm Multi-format Retail Peer | E10: 10.864 | F10: 20.70428 | G10: Calculated | H10: TRUE | I10: yfinance

Sheet Valuation
A1: Valuation por Multiplos | Ponte EV para Equity
A3: Cenario | B3: Multiplo | C3: EBITDA | D3: EV implicito | E3: Divida liquida | F3: Equity value | G3: Acoes | H3: Preco justo | I3: Preco atual | J3: Upside | K3: Metodologia | L3: Leitura qualitativa
A4: Conservative Case | B4: 6.3828474 | C4: 1600 | D4: =B4*C4 | E4: 736 | F4: =D4-E4 | G4: 2300047621 | H4: =F4*1000000/G4 | I4: 4.26 | J4: =H4/I4-1 | K4: 25th percentile of full traded peer set, including GPA | L4: Stress case: downside risk if weak SSS and margin pressure persist.
A5: Domestic Listed Median | B5: 4.2011303 | C5: 1600 | D5: =B5*C5 | E5: 736 | F5: =D5-E5 | G5: 2300047621 | H5: =F5*1000000/G5 | I5: 4.26 | J5: =H5/I5-1 | K5: Median of Brazilian listed peers, including distressed GPA | L5: Stress case: downside risk if weak SSS and margin pressure persist.
A6: Domestic Core Case | B6: 6.1047965 | C6: 1600 | D6: =B6*C6 | E6: 736 | F6: =D6-E6 | G6: 2300047621 | H6: =F6*1000000/G6 | I6: 4.26 | J6: =H6/I6-1 | K6: Assai-only case as closest domestic listed comparable | L6: Scenario output should be interpreted with 1T26 operating caution.
A7: Expanded LatAm ex-Distressed Median | B7: 7.398 | C7: 1600 | D7: =B7*C7 | E7: 736 | F7: =D7-E7 | G7: 2300047621 | H7: =F7*1000000/G7 | I7: 4.26 | J7: =H7/I7-1 | K7: Median of traded peers excluding distressed GPA and delisted Carrefour Brasil | L7: Base case: moderate upside, but operational caution required.
A8: Expanded LatAm including GPA Median | B8: 7.3075 | C8: 1600 | D8: =B8*C8 | E8: 736 | F8: =D8-E8 | G8: 2300047621 | H8: =F8*1000000/G8 | I8: 4.26 | J8: =H8/I8-1 | K8: Median of all traded peers, including GPA | L8: Scenario output should be interpreted with 1T26 operating caution.
A9: Upside Case | B9: 9.841 | C9: 1600 | D9: =B9*C9 | E9: 736 | F9: =D9-E9 | G9: 2300047621 | H9: =F9*1000000/G9 | I9: 4.26 | J9: =H9/I9-1 | K9: Higher of GMAT3 current EV/EBITDA and ex-distressed peer 75th percentile | L9: Bull case: upside increases if SSS normalizes and margin protection continues.

Sheet Sensibilidade
A1: Sensibilidade de Preco Justo
A4: EBITDA / Multiplo | B4: 5.5 | C4: 6.5 | D4: 7 | E4: 7.5 | F4: 8 | G4: 9 | H4: 10
A5: 1400 | B5: =($A5*B$4-736)*1000000/2300047621.0 | C5: =($A5*C$4-736)*1000000/2300047621.0 | D5: =($A5*D$4-736)*1000000/2300047621.0 | E5: =($A5*E$4-736)*1000000/2300047621.0 | F5: =($A5*F$4-736)*1000000/2300047621.0 | G5: =($A5*G$4-736)*1000000/2300047621.0 | H5: =($A5*H$4-736)*1000000/2300047621.0
A6: 1500 | B6: =($A6*B$4-736)*1000000/2300047621.0 | C6: =($A6*C$4-736)*1000000/2300047621.0 | D6: =($A6*D$4-736)*1000000/2300047621.0 | E6: =($A6*E$4-736)*1000000/2300047621.0 | F6: =($A6*F$4-736)*1000000/2300047621.0 | G6: =($A6*G$4-736)*1000000/2300047621.0 | H6: =($A6*H$4-736)*1000000/2300047621.0
A7: 1600 | B7: =($A7*B$4-736)*1000000/2300047621.0 | C7: =($A7*C$4-736)*1000000/2300047621.0 | D7: =($A7*D$4-736)*1000000/2300047621.0 | E7: =($A7*E$4-736)*1000000/2300047621.0 | F7: =($A7*F$4-736)*1000000/2300047621.0 | G7: =($A7*G$4-736)*1000000/2300047621.0 | H7: =($A7*H$4-736)*1000000/2300047621.0
A8: 1700 | B8: =($A8*B$4-736)*1000000/2300047621.0 | C8: =($A8*C$4-736)*1000000/2300047621.0 | D8: =($A8*D$4-736)*1000000/2300047621.0 | E8: =($A8*E$4-736)*1000000/2300047621.0 | F8: =($A8*F$4-736)*1000000/2300047621.0 | G8: =($A8*G$4-736)*1000000/2300047621.0 | H8: =($A8*H$4-736)*1000000/2300047621.0
A9: 1800 | B9: =($A9*B$4-736)*1000000/2300047621.0 | C9: =($A9*C$4-736)*1000000/2300047621.0 | D9: =($A9*D$4-736)*1000000/2300047621.0 | E9: =($A9*E$4-736)*1000000/2300047621.0 | F9: =($A9*F$4-736)*1000000/2300047621.0 | G9: =($A9*G$4-736)*1000000/2300047621.0 | H9: =($A9*H$4-736)*1000000/2300047621.0

Sheet Lucro Setor
A1: Lucro Liquido Setorial
A3: Lucro liquido setorial calculado separadamente para Brasil em BRL milhões. Nao somamos LatAm porque Walmex, Chedraui, Soriana e Cencosud reportam em outras moedas.
A5: Recorte | B5: Moeda | C5: Base | D5: Empresas | E5: Qtd. | F5: Lucro liquido total | G5: Lucro positivo | H5: Leitura
A6: Brazil listed food retail incl. GMAT3 and GPA | B6: BRL | C6: 1Q26 annualized | D6: GMAT3.SA, ASAI3.SA, PCAR3.SA | E6: 3 | F6: -3840 | G6: 1548 | H6: Recorte mais limpo para lucro positivo.
A7: Brazil peers only incl. GPA | B7: BRL | C7: 1Q26 annualized | D7: ASAI3.SA, PCAR3.SA | E7: 2 | F7: -4692 | G7: 696 | H7: Recorte mais limpo para lucro positivo.
A8: Brazil peers ex-distressed GPA | B8: BRL | C8: 1Q26 annualized | D8: ASAI3.SA | E8: 1 | F8: 696 | G8: 696 | H8: Recorte mais limpo para lucro positivo.

Sheet Operacional
A1: Overlay Operacional 1T26
A3: O valuation aponta upside moderado, mas os dados operacionais do 1T26 reduzem a convicção. O ponto central é que a empresa protegeu margem bruta, mas sofreu com SSS negativo, deflação alimentar e desalavancagem operacional.
A5: Métrica | B5: Valor | C5: Unidade | D5: Leitura | E5: Impacto na tese | F5: Mensagem para apresentação
A6: Net revenue growth YoY | B6: 12.9 | C6: % | D6: Revenue still grew, helped by consolidation and channel growth. | E6: Positivo, mas não suficiente para compensar pressão de lucro. | F6: Upside existe, mas precisa ser lido com cautela operacional.
A7: Net income growth YoY | B7: -21.8 | C7: % | D7: Profitability deteriorated despite revenue growth. | E7: Negativo para convicção de curto prazo. | F7: Upside existe, mas precisa ser lido com cautela operacional.
A8: Same-store sales growth | B8: -7.3 | C8: % | D8: Negative SSS points to weaker mature-store momentum. | E8: Principal alerta operacional. | F8: Upside existe, mas precisa ser lido com cautela operacional.
A9: Gross margin | B9: 22.9 | C9: % | D9: Margin protection worked at the gross profit level. | E9: Mostra preservação de margem. | F9: Upside existe, mas precisa ser lido com cautela operacional.
A10: EBITDA margin pre-IFRS 16 | B10: 4.3 | C10: % | D10: Pre-IFRS profitability remains pressured. | E10: Mostra pressão operacional antes do efeito IFRS 16. | F10: Upside existe, mas precisa ser lido com cautela operacional.
A11: EBITDA margin post-IFRS 16 | B11: 5.8 | C11: % | D11: Post-IFRS 16 EBITDA margin also declined YoY. | E11: Margem reportada ainda pressionada. | F11: Upside existe, mas precisa ser lido com cautela operacional.
A12: EBITDA pre-IFRS 16 | B12: 399.8 | C12: BRL mn | D12: Used as an operating quality reference versus annualized EBITDA. | E12: Base operacional mais conservadora. | F12: Upside existe, mas precisa ser lido com cautela operacional.
A13: EBITDA post-IFRS 16 | B13: 543 | C13: BRL mn | D13: Reported post-IFRS EBITDA reference. | E13: Referência reportada pós-arrendamento. | F13: Upside existe, mas precisa ser lido com cautela operacional.
A16: Pilar operacional | B16: Tese | C16: Risco
A17: Crescimento regional | B17: Força regional ainda sustenta a tese estrutural. | C17: Expansão fora do core pode reduzir retorno.
A18: Maturação de lojas | B18: Normalização de SSS é chave para o re-rating. | C18: SSS negativo prolongado limita upside.
A19: Logística e distribuição | B19: Eficiência logística pode proteger margem. | C19: Custo logístico e ruptura podem pressionar rentabilidade.
A20: Margem EBITDA | B20: Preservação de margem é positiva, mas não pode depender de queda de volume. | C20: Trade-off margem vs volume reduz qualidade do crescimento.
A21: Competição no atacarejo | B21: Setor segue estruturalmente relevante. | C21: Assaí, Atacadão e players regionais pressionam preços.

Sheet Fontes
A1: Fontes e Data-base
A3: ID | B3: Item | C3: Empresa | D3: Ticker | E3: Periodo/Data | F3: Tipo | G3: Fonte | H3: Uso
A4: SRC001 | B4: 1T26 earnings release | C4: Grupo Mateus | D4: GMAT3.SA | E4: 1T26 | F4: Company filing / IR | G4: https://ri.grupomateus.com.br/central-de-resultados/ | H4: Raw Brazilian fundamentals
A5: SRC002 | B5: 1T26 earnings release | C5: Assai | D5: ASAI3.SA | E5: 1T26 | F5: Company filing / IR | G5: https://ri.assai.com.br/informacoes-financeiras/resultados-trimestrais/ | H5: Raw Brazilian fundamentals
A6: SRC003 | B6: 1T26 earnings release | C6: GPA | D6: PCAR3.SA | E6: 1T26 | F6: Company filing / IR | G6: https://www.gpari.com.br/ | H6: Raw Brazilian fundamentals
A7: SRC004 | B7: Market data and LatAm multiples | C7: Expanded peer group | E7: 2026-05-31 | F7: Market data | G7: https://finance.yahoo.com/ | H7: Current prices market caps EV EBITDA net income and multiples
A8: SRC005 | B8: Carrefour Brasil delisting | C8: Carrefour Brasil / Atacadao | D8: CRFB3.SA | E8: 2025-05-30 | F8: Market/news source | G8: https://investalk.bb.com.br/noticias/mercado/acao-do-carrefour-crfb3-da-adeus-a-b3-como-ficam-os-acionistas | H8: Peer treatment
A9: SRC006 | B9: Grupo Mateus operating strategy | C9: Grupo Mateus | D9: GMAT3.SA | E9: current | F9: Company IR | G9: https://ri.grupomateus.com.br/en/the-group/strategy/ | H9: Operating thesis
A10: SRC007 | B10: Peer selection framework | C10: All peers | E10: 2026-05-31 | F10: Analyst judgment | G10: Internal model | H10: Peer group classification
A11: SRC008 | B11: 1T26 operating evidence | C11: Grupo Mateus | D11: GMAT3.SA | E11: 2026-05-14 | F11: News / earnings analysis | G11: https://www.moneytimes.com.br/grupo-mateus-gmat3-ve-lucro-cair-218-no-1t26-para-r-2129-milhoes/ | H11: Operational overlay and risk interpretation

Sheet Graficos
A1: Graficos para Relatorio
